LICENSE
docformatter/__init__.py
docformatter/__main__.py
docformatter/__pkginfo__.py
docformatter/configuration.py
docformatter/encode.py
docformatter/format.py
docformatter/strings.py
docformatter/syntax.py
docformatter/util.py
docformatter-1.7.2.dist-info/LICENSE
docformatter-1.7.2.dist-info/METADATA
docformatter-1.7.2.dist-info/WHEEL
docformatter-1.7.2.dist-info/entry_points.txt
docformatter-1.7.2.dist-info/RECORD
