Metadata-Version: 2.1
Name: docformatter
Version: 1.7.2
Summary: Formats docstrings to follow PEP 257
Home-page: https://github.com/PyCQA/docformatter
License: Expat
Keywords: PEP 257,pep257,style,formatter,docstrings
Author: Steven Myint
Maintainer: Doyle Rowland
Maintainer-email: doyle.rowland@reliaqual.com
Requires-Python: >=3.7,<4.0
Classifier: Environment :: Console
Classifier: Intended Audience :: Developers
Classifier: License :: OSI Approved :: MIT License
Classifier: License :: Other/Proprietary License
Classifier: Programming Language :: Python :: 3
Classifier: Programming Language :: Python :: 3.7
Classifier: Programming Language :: Python :: 3.8
Classifier: Programming Language :: Python :: 3.9
Classifier: Programming Language :: Python :: 3.10
Classifier: Programming Language :: Python :: 3.11
Classifier: Programming Language :: Python :: Implementation
Classifier: Programming Language :: Python :: Implementation :: CPython
Classifier: Programming Language :: Python :: Implementation :: PyPy
Provides-Extra: tomli
Requires-Dist: charset_normalizer (>=3.0.0,<4.0.0)
Requires-Dist: tomli (>=2.0.0,<3.0.0) ; (python_version < "3.11") and (extra == "tomli")
Requires-Dist: untokenize (>=0.1.1,<0.2.0)
Project-URL: Documentation, https://github.com/PyCQA/docformatter
Project-URL: Repository, https://github.com/PyCQA/docformatter
